minesweeper/__init__.py
minesweeper/minesweeper.py
minesweeper_python-0.0.4.dist-info/LICENSE
minesweeper_python-0.0.4.dist-info/METADATA
minesweeper_python-0.0.4.dist-info/WHEEL
minesweeper_python-0.0.4.dist-info/top_level.txt
minesweeper_python-0.0.4.dist-info/RECORD
